{
  "blog_id": "paikorea",
  "blog_url": "https://blog.naver.com/paikorea",
  "rss_url": "https://rss.blog.naver.com/paikorea.xml",
  "checked_at": "2026-07-02T08:00:27.615152+00:00",
  "count": 6,
  "posts": [
    {
      "title": "세일러 펜뷔페 새로운 10가지 색상이 출시되었습니다!",
      "link": "https://blog.naver.com/paikorea/224316555933?fromRss=true&trackingCode=rss",
      "published": "Mon, 15 Jun 2026 15:39:14 +0900",
      "text_length": 340,
      "image_count_rss": 1,
      "paragraph_count_estimate": 1,
      "excerpt": "안녕하세요~~ 블블샵 Jen입니다! 오늘은 오프라인 매장에서 진행하는 '세일러 펜뷔페'의 NEW 색상 소식을 들고 왔는데요! 블블샵에서는 바로 오늘, 6월 15일부터 판매를 시작합니다~~ 그럼 영롱한 색감의 신규 색상을 함께 만나보실까요?! New! 10 Colors 스트로베리 | 애프리콧 | 징코 넛츠 | 제이드 | 사파이어 | 울프 | 아케비아 | 사쿠라모찌 | 래빗 | 스켈레톤 플라워☁ 과일처럼 맑고 화사한 색감의 스트로베리, 애프리콧 흔하지 않은 오묘한 느낌의 징코 넛츠, 제이드 신비롭게 딥한 색감의 사파이어, 울프, 아케비아도 있답니다~ 이번 신규 컬러 너무 예쁘지 않나요? 그리고......."
    },
    {
      "title": "블블샵 홈페이지 리뉴얼 완료! 6월 할인 쿠폰 EVENT",
      "link": "https://blog.naver.com/paikorea/224311794359?fromRss=true&trackingCode=rss",
      "published": "Wed, 10 Jun 2026 15:24:19 +0900",
      "text_length": 359,
      "image_count_rss": 1,
      "paragraph_count_estimate": 1,
      "excerpt": "안녕하세요 :> 블블샵 온라인 홈페이지 리뉴얼 & 혜택 소식으로 찾아온 Jen 입니다! 우선 리뉴얼된 홈페이지를 함께 구경해 보시고! 6월 이벤트와 새로운 소식도 이어서 소개해 드릴게요. ✨ New ✨ BlueBlack Online Shop 이번 홈페이지 리뉴얼의 포인트는.. 취향을 제안하는 블블샵의 큐레이션과 한눈에 원하는 것을 찾을 수 있는 직관성인데요! 지금부터 같이 구경해 보실까요~?! 메인 페이지에서 바로 블블샵 신제품들을 구경하실 수 있는데요! 매일매일 새롭게 도착하는 아이템들을 간편하게 만나보세요~~ 테마에 맞는 아이템들을 추천해 드리는 공간도 생겼습니다! 어떤 제품을 구입할까 고민되는 분들이라면, 새로운 취향......."
    },
    {
      "title": "라미 만년필 무료 각인 이벤트｜사파리·알스타·룩스·스튜디오 대상",
      "link": "https://blog.naver.com/paikorea/224299204915?fromRss=true&trackingCode=rss",
      "published": "Thu, 28 May 2026 17:30:27 +0900",
      "text_length": 345,
      "image_count_rss": 1,
      "paragraph_count_estimate": 1,
      "excerpt": "안녕하세요! 블루블랙 펜샵 Kevin 입니다. 오늘은 라미 만년필을 보고 계셨던 분들께 반가운 소식을 하나 전해드리려고 합니다. 바로 라미 만년필 무료 각인 이벤트입니다. 이벤트 대상 라미 만년필을 구매하시면 레이저 각인을 무료로 진행해 드리고 있습니다. 라미 만년필은 선물용으로도 정말 많이 찾아주시는 제품인데요. 여기에 이름, 이니셜, 짧은 문구가 더해지면 같은 만년필이라도 조금 더 특별한 선물이 될 수 있습니다. ✨ 졸업 선물, 입사 선물, 생일 선물, 기업 기념품처럼 의미를 담아 준비하는 선물이라면 이번 이벤트를 활용해 보셔도 좋을 것 같습니다! 라미 만년필 ️ 무료 각인 이벤트 이번 이벤트는......."
    },
    {
      "title": "기업 특판 및 단체 선물 추천, 라미 사파리 샤프/만년필",
      "link": "https://blog.naver.com/paikorea/224279055897?fromRss=true&trackingCode=rss",
      "published": "Fri, 08 May 2026 16:25:29 +0900",
      "text_length": 356,
      "image_count_rss": 1,
      "paragraph_count_estimate": 1,
      "excerpt": "안녕하세요! 블루블랙 펜샵 Kevin 입니다. 오늘은 기업 특판, 단체 주문, 각종 기념 선물로 추천드리기 좋은 샤프와 만년필을 소개해 드리려고 합니다⭐ 다양한 색상과 실용적인 디자인으로 꾸준히 사랑받고 있는 입문용 필기구의 대표 모델, 라미 사파리 샤프/만년필입니다! ↓ 하단 링크를 누르시면 제품을 보실 수 있습니다! ↓ 라미 사파리는 독일 필기구 브랜드 LAMY 의 대표 제품입니다. 튼튼한 바디와 각진 디자인으로 책상 위에서 쉽게 굴러가지 않고, 손에 편안하게 잡히는 삼각 그립부가 안정적으로 필기할 수 있게 해줍니다. 또한 교체 가능한 펜촉과 실용적인 클립까지 갖추고 있어 학생과 직장인 모두 사용하기 좋습니다. ?......."
    },
    {
      "title": "코니퍼 노트 1+1 행사",
      "link": "https://blog.naver.com/paikorea/224253347848?fromRss=true&trackingCode=rss",
      "published": "Wed, 15 Apr 2026 15:54:39 +0900",
      "text_length": 364,
      "image_count_rss": 1,
      "paragraph_count_estimate": 1,
      "excerpt": "안녕하세요! 블루블랙 펜샵의 Keily 입니다! 블블샵의 새로운 행사 소식을 들고 찾아왔어요! 바로 코니퍼 노트 1+1 행사입니다! 자세한 안내는 아래에서 보여드릴게요!✨ 코니퍼(Conifer)는 대만의 문구 브랜드입니다! 코니퍼의 노트에 사용되는 용지는 KBU 용지로 코니퍼의 자체 제작 용지라고 해요! KBU 용지는 만년필 또는 딥펜 사용 시 잉크의 실번짐과 획번짐이 없어 만년필, 딥펜 뿐만아니라 워터브러쉬 사용이나 캘리그라피에도 적합한 종이입니다. 현재 블루블랙 펜샵은 6종의 코니퍼 노트를 판매 중입니다! 뷰 노트 (B6/A5/B5) 단단한 하드커버와 고무줄로 노트 표지와 내지 손상 걱정 없이 사용할 수 있는 노트로, 블랙, 스......."
    },
    {
      "title": "[톤랜드] 책상 위를 정돈해 줄 문구 브랜드 | 책갈피, 클립, 연필캡, 클립보드, 6공 다이어리, 가죽 커버, 노트 속지",
      "link": "https://blog.naver.com/paikorea/224242748157?fromRss=true&trackingCode=rss",
      "published": "Mon, 06 Apr 2026 16:25:20 +0900",
      "text_length": 352,
      "image_count_rss": 1,
      "paragraph_count_estimate": 1,
      "excerpt": "안녕하세요! 블루블랙 펜샵 Jen 입니다. 오늘은 블루블랙 펜샵에 새로 입점된 브랜드! 톤랜드를 소개해 드릴게요.✨ 기본에 집중한 간결한 디자인으로 데스크 환경을 정리해 줄 제품들이 가득한데요~ 지금부터 하나씩 같이 구경하러 가보시죠! ( 책갈피, 클립, 연필캡, 클립보드, 6공 다이어리, 가죽 커버, 노트 속지 등 ) ️ 마그넷 인덱스 책갈피 / 8 colors ️ 빠지거나 구겨질 걱정 없는! 자석 책갈피인데요. 책에 끼우면 인덱스 모양이 된답니다. 가죽의 고급스러움과 실용성이 동시에 있는 제품이네요.. 플라스틱 클립 / 8 colors 일상에서 자주 사용하는 클립! 내가 좋아하는 색이 담긴 클립을 선택한다면......."
    }
  ],
  "summary": {
    "average_text_length": 353,
    "min_text_length": 340,
    "max_text_length": 364,
    "average_image_count_rss": 1.0,
    "note": "RSS description 기준. 네이버 에디터의 실제 전체 이미지 수와 다를 수 있음."
  }
}